Metadata-Version: 2.4
Name: langchain-gigachat-lc1
Version: 0.4.0b4
Summary: An integration package connecting GigaChat and LangChain
Project-URL: Repository, https://github.com/ai-forever/langchain-gigachat
Project-URL: Source Code, https://github.com/ai-forever/langchain-gigachat/tree/master/libs/gigachat
License-Expression: MIT
License-File: LICENSE
Requires-Python: <4,>=3.10
Requires-Dist: gigachat<0.3,>=0.2.0b2
Requires-Dist: langchain-core<2,>=1
